elli/__init__.py
elli/experiment.py
elli/materials.py
elli/result.py
elli/solver.py
elli/solver2x2.py
elli/solver4x4.py
elli/structure.py
elli/units.py
elli/utils.py
elli/database/__init__.py
elli/database/materials_db.py
elli/database/refractive_index_info.py
elli/dispersions/__init__.py
elli/dispersions/base_dispersion.py
elli/dispersions/cauchy.py
elli/dispersions/cauchy_custom.py
elli/dispersions/cauchy_urbach.py
elli/dispersions/cody_lorentz.py
elli/dispersions/constant_refractive_index.py
elli/dispersions/drude_energy.py
elli/dispersions/drude_resistivity.py
elli/dispersions/epsilon_inf.py
elli/dispersions/formula.py
elli/dispersions/gaussian.py
elli/dispersions/lorentz_energy.py
elli/dispersions/lorentz_lambda.py
elli/dispersions/poles.py
elli/dispersions/polynomial.py
elli/dispersions/pseudo_dielectric.py
elli/dispersions/sellmeier.py
elli/dispersions/sellmeier_custom.py
elli/dispersions/table_epsilon.py
elli/dispersions/table_index.py
elli/dispersions/table_spectraray.py
elli/dispersions/tanguy.py
elli/dispersions/tauc_lorentz.py
elli/fitting/__init__.py
elli/fitting/decorator.py
elli/fitting/decorator_mmatrix.py
elli/fitting/decorator_psi_delta.py
elli/fitting/params_hist.py
elli/formula_parser/__init__.py
elli/formula_parser/dispersion_function_grammar.lark
elli/formula_parser/parser.py
elli/importer/__init__.py
elli/importer/accurion.py
elli/importer/nexus.py
elli/importer/spectraray.py
elli/importer/woollam.py
elli/kkr/__init__.py
elli/kkr/kkr.py
elli/plot/__init__.py
elli/plot/mueller_matrix.py
elli/plot/structure.py
pyElli-0.21.1.dist-info/AUTHORS.md
pyElli-0.21.1.dist-info/LICENSE.txt
pyElli-0.21.1.dist-info/METADATA
pyElli-0.21.1.dist-info/WHEEL
pyElli-0.21.1.dist-info/top_level.txt
pyElli-0.21.1.dist-info/RECORD
