Metadata-Version: 2.1
Name: pyElli
Version: 0.21.1
Summary: An ellipsometry analysis tool for reproducible and comprehensible building of optical models.
Author-email: Marius Müller <marius.mueller@physik.uni-giessen.de>, Florian Dobener <pyelli@schroedingerscat.org>
License: GNU GENERAL PUBLIC LICENSE
Project-URL: homepage, https://github.com/PyEllips/pyElli/
Project-URL: repository, https://github.com/PyEllips/pyElli/
Project-URL: documentation, https://pyelli.readthedocs.io/en/latest/
Project-URL: changelog, https://github.com/PyEllips/pyElli/blob/master/CHANGELOG.md
Project-URL: tracker, https://github.com/PyEllips/pyElli/issues
Project-URL: download, https://github.com/PyEllips/pyElli/releases
Classifier: Development Status :: 4 - Beta
Classifier: Programming Language :: Python :: 3.8
Classifier: Programming Language :: Python :: 3.9
Classifier: Programming Language :: Python :: 3.10
Classifier: Programming Language :: Python :: 3.11
Classifier: Programming Language :: Python :: 3.12
Requires-Python: >=3.8
License-File: LICENSE.txt
License-File: AUTHORS.md
Requires-Dist: scipy
Requires-Dist: numpy >=1.20
Requires-Dist: pandas >=1.0.0
Requires-Dist: h5py
Requires-Dist: pyyaml
Requires-Dist: importlib-resources
Requires-Dist: rapidfuzz
Requires-Dist: lark >=1.1.5
Requires-Dist: pint
Requires-Dist: chardet
Requires-Dist: numpy <2.0.0 ; python_version < "3.10"
Provides-Extra: dev
Requires-Dist: pytest ; extra == 'dev'
Requires-Dist: pytest-benchmark ; extra == 'dev'
Requires-Dist: pytest-cov ; extra == 'dev'
Requires-Dist: nbmake ; extra == 'dev'
Requires-Dist: ruff ==0.4.8 ; extra == 'dev'
Requires-Dist: uv ; extra == 'dev'
Requires-Dist: pre-commit ; extra == 'dev'
Provides-Extra: fitting
Requires-Dist: ipython ; extra == 'fitting'
Requires-Dist: ipywidgets ; extra == 'fitting'
Requires-Dist: plotly ; extra == 'fitting'
Requires-Dist: matplotlib ; extra == 'fitting'
Requires-Dist: lmfit ; extra == 'fitting'
